gw2apy/__init__.py
gw2apy/client.py
gw2apy/endpoints/__init__.py
gw2apy/endpoints/account.py
gw2apy/endpoints/achievements.py
gw2apy/endpoints/backstory.py
gw2apy/endpoints/build.py
gw2apy/endpoints/characters.py
gw2apy/endpoints/colors.py
gw2apy/endpoints/commerce.py
gw2apy/endpoints/continents.py
gw2apy/endpoints/currencies.py
gw2apy/endpoints/dailycrafting.py
gw2apy/endpoints/dungeons.py
gw2apy/endpoints/emblem.py
gw2apy/endpoints/emotes.py
gw2apy/endpoints/endpoint.py
gw2apy/endpoints/files.py
gw2apy/endpoints/finishers.py
gw2apy/endpoints/gliders.py
gw2apy/endpoints/guild.py
gw2apy/endpoints/home.py
gw2apy/endpoints/items.py
gw2apy/endpoints/itemstats.py
gw2apy/endpoints/legends.py
gw2apy/endpoints/mailcarriers.py
gw2apy/endpoints/mapchests.py
gw2apy/endpoints/maps.py
gw2apy/endpoints/masteries.py
gw2apy/endpoints/materials.py
gw2apy/endpoints/minis.py
gw2apy/endpoints/mounts.py
gw2apy/endpoints/novelties.py
gw2apy/endpoints/outfits.py
gw2apy/endpoints/pets.py
gw2apy/endpoints/professions.py
gw2apy/endpoints/pvp.py
gw2apy/endpoints/quaggans.py
gw2apy/endpoints/quests.py
gw2apy/endpoints/races.py
gw2apy/endpoints/raids.py
gw2apy/endpoints/recipes.py
gw2apy/endpoints/skills.py
gw2apy/endpoints/skins.py
gw2apy/endpoints/specializations.py
gw2apy/endpoints/stories.py
gw2apy/endpoints/titles.py
gw2apy/endpoints/tokeninfo.py
gw2apy/endpoints/traits.py
gw2apy/endpoints/worldbosses.py
gw2apy/endpoints/worlds.py
gw2apy/endpoints/wvw.py
tests/__init__.py
tests/simple_test.py
gw2apy-0.0.2.dist-info/LICENSE
gw2apy-0.0.2.dist-info/METADATA
gw2apy-0.0.2.dist-info/WHEEL
gw2apy-0.0.2.dist-info/top_level.txt
gw2apy-0.0.2.dist-info/RECORD
