Metadata-Version: 2.1
Name: gw2apy
Version: 0.0.2
Summary: Guild Wars 2 API Python Wrapper
Home-page: https://github.com/GuillaumeRochette/gw2apy/
Author: Guillaume Rochette
Author-email: rochette.guillaume@gmail.com
License: UNKNOWN
Project-URL: Bug Reports, https://github.com/GuillaumeRochette/gw2apy/issues
Project-URL: Source, https://github.com/GuillaumeRochette/gw2apy/
Platform: UNKNOWN
Classifier: Development Status :: 3 - Alpha
Classifier: Intended Audience :: Developers
Classifier: License :: OSI Approved :: MIT License
Classifier: Programming Language :: Python :: 3
Classifier: Programming Language :: Python :: 3.6
Classifier: Programming Language :: Python :: 3.7
Classifier: Programming Language :: Python :: 3.8
Classifier: Operating System :: OS Independent
Classifier: Natural Language :: English
Requires-Python: >=3.6
Requires-Dist: requests-futures (>=1.0.0)
Requires-Dist: ratelimit (>=2.2.1)
